[
    {
        "('Unnamed: 0_level_0', 'Player')": "\u00c1lvaro Gim\u00e9nez",
        "('Unnamed: 1_level_0', '#')": 24.0,
        "('Unnamed: 2_level_0', 'Nation')": "es ESP",
        "('Unnamed: 3_level_0', 'Pos')": "FW",
        "('Unnamed: 4_level_0', 'Age')": "28-135",
        "('Unnamed: 5_level_0', 'Min')": 90,
        "('Total', 'Cmp')": 17,
        "('Total', 'Att')": 22,
        "('Total', 'Cmp%')": 77.3,
        "('Total', 'TotDist')": 190,
        "('Total', 'PrgDist')": 28,
        "('Short', 'Cmp')": 12,
        "('Short', 'Att')": 13,
        "('Short', 'Cmp%')": 92.3,
        "('Medium', 'Cmp')": 4,
        "('Medium', 'Att')": 4,
        "('Medium', 'Cmp%')": 100.0,
        "('Long', 'Cmp')": 0,
        "('Long', 'Att')": 1,
        "('Long', 'Cmp%')": 0.0,
        "('Unnamed: 20_level_0', 'Ast')": 0,
        "('Unnamed: 21_level_0', 'xAG')": 0.0,
        "('Unnamed: 22_level_0', 'xA')": 0.0,
        "('Unnamed: 23_level_0', 'KP')": 0,
        "('Unnamed: 24_level_0', '1/3')": 0,
        "('Unnamed: 25_level_0', 'PPA')": 0,
        "('Unnamed: 26_level_0', 'CrsPA')": 0,
        "('Unnamed: 27_level_0', 'PrgP')": 1
    },
    {
        "('Unnamed: 0_level_0', 'Player')": "Lukas Jutkiewicz",
        "('Unnamed: 1_level_0', '#')": 10.0,
        "('Unnamed: 2_level_0', 'Nation')": "eng ENG",
        "('Unnamed: 3_level_0', 'Pos')": "FW",
        "('Unnamed: 4_level_0', 'Age')": "30-187",
        "('Unnamed: 5_level_0', 'Min')": 90,
        "('Total', 'Cmp')": 14,
        "('Total', 'Att')": 31,
        "('Total', 'Cmp%')": 45.2,
        "('Total', 'TotDist')": 180,
        "('Total', 'PrgDist')": 41,
        "('Short', 'Cmp')": 10,
        "('Short', 'Att')": 19,
        "('Short', 'Cmp%')": 52.6,
        "('Medium', 'Cmp')": 4,
        "('Medium', 'Att')": 11,
        "('Medium', 'Cmp%')": 36.4,
        "('Long', 'Cmp')": 0,
        "('Long', 'Att')": 0,
        "('Long', 'Cmp%')": null,
        "('Unnamed: 20_level_0', 'Ast')": 0,
        "('Unnamed: 21_level_0', 'xAG')": 0.0,
        "('Unnamed: 22_level_0', 'xA')": 0.0,
        "('Unnamed: 23_level_0', 'KP')": 0,
        "('Unnamed: 24_level_0', '1/3')": 1,
        "('Unnamed: 25_level_0', 'PPA')": 0,
        "('Unnamed: 26_level_0', 'CrsPA')": 0,
        "('Unnamed: 27_level_0', 'PrgP')": 3
    },
    {
        "('Unnamed: 0_level_0', 'Player')": "Fran Villalba",
        "('Unnamed: 1_level_0', '#')": 17.0,
        "('Unnamed: 2_level_0', 'Nation')": "es ESP",
        "('Unnamed: 3_level_0', 'Pos')": "LM",
        "('Unnamed: 4_level_0', 'Age')": "21-143",
        "('Unnamed: 5_level_0', 'Min')": 72,
        "('Total', 'Cmp')": 32,
        "('Total', 'Att')": 43,
        "('Total', 'Cmp%')": 74.4,
        "('Total', 'TotDist')": 766,
        "('Total', 'PrgDist')": 226,
        "('Short', 'Cmp')": 7,
        "('Short', 'Att')": 7,
        "('Short', 'Cmp%')": 100.0,
        "('Medium', 'Cmp')": 11,
        "('Medium', 'Att')": 14,
        "('Medium', 'Cmp%')": 78.6,
        "('Long', 'Cmp')": 11,
        "('Long', 'Att')": 15,
        "('Long', 'Cmp%')": 73.3,
        "('Unnamed: 20_level_0', 'Ast')": 0,
        "('Unnamed: 21_level_0', 'xAG')": 0.1,
        "('Unnamed: 22_level_0', 'xA')": 0.1,
        "('Unnamed: 23_level_0', 'KP')": 3,
        "('Unnamed: 24_level_0', '1/3')": 4,
        "('Unnamed: 25_level_0', 'PPA')": 1,
        "('Unnamed: 26_level_0', 'CrsPA')": 0,
        "('Unnamed: 27_level_0', 'PrgP')": 4
    },
    {
        "('Unnamed: 0_level_0', 'Player')": "Odin Bailey",
        "('Unnamed: 1_level_0', '#')": 37.0,
        "('Unnamed: 2_level_0', 'Nation')": "eng ENG",
        "('Unnamed: 3_level_0', 'Pos')": "LM,WB",
        "('Unnamed: 4_level_0', 'Age')": "19-297",
        "('Unnamed: 5_level_0', 'Min')": 18,
        "('Total', 'Cmp')": 8,
        "('Total', 'Att')": 11,
        "('Total', 'Cmp%')": 72.7,
        "('Total', 'TotDist')": 90,
        "('Total', 'PrgDist')": 27,
        "('Short', 'Cmp')": 6,
        "('Short', 'Att')": 6,
        "('Short', 'Cmp%')": 100.0,
        "('Medium', 'Cmp')": 2,
        "('Medium', 'Att')": 3,
        "('Medium', 'Cmp%')": 66.7,
        "('Long', 'Cmp')": 0,
        "('Long', 'Att')": 1,
        "('Long', 'Cmp%')": 0.0,
        "('Unnamed: 20_level_0', 'Ast')": 0,
        "('Unnamed: 21_level_0', 'xAG')": 0.1,
        "('Unnamed: 22_level_0', 'xA')": 0.0,
        "('Unnamed: 23_level_0', 'KP')": 1,
        "('Unnamed: 24_level_0', '1/3')": 1,
        "('Unnamed: 25_level_0', 'PPA')": 0,
        "('Unnamed: 26_level_0', 'CrsPA')": 0,
        "('Unnamed: 27_level_0', 'PrgP')": 1
    },
    {
        "('Unnamed: 0_level_0', 'Player')": "Ivan \u0160unji\u0107",
        "('Unnamed: 1_level_0', '#')": 34.0,
        "('Unnamed: 2_level_0', 'Nation')": "hr CRO",
        "('Unnamed: 3_level_0', 'Pos')": "CM",
        "('Unnamed: 4_level_0', 'Age')": "22-357",
        "('Unnamed: 5_level_0', 'Min')": 90,
        "('Total', 'Cmp')": 31,
        "('Total', 'Att')": 40,
        "('Total', 'Cmp%')": 77.5,
        "('Total', 'TotDist')": 478,
        "('Total', 'PrgDist')": 149,
        "('Short', 'Cmp')": 11,
        "('Short', 'Att')": 12,
        "('Short', 'Cmp%')": 91.7,
        "('Medium', 'Cmp')": 15,
        "('Medium', 'Att')": 19,
        "('Medium', 'Cmp%')": 78.9,
        "('Long', 'Cmp')": 2,
        "('Long', 'Att')": 6,
        "('Long', 'Cmp%')": 33.3,
        "('Unnamed: 20_level_0', 'Ast')": 0,
        "('Unnamed: 21_level_0', 'xAG')": 0.0,
        "('Unnamed: 22_level_0', 'xA')": 0.0,
        "('Unnamed: 23_level_0', 'KP')": 0,
        "('Unnamed: 24_level_0', '1/3')": 8,
        "('Unnamed: 25_level_0', 'PPA')": 0,
        "('Unnamed: 26_level_0', 'CrsPA')": 0,
        "('Unnamed: 27_level_0', 'PrgP')": 2
    },
    {
        "('Unnamed: 0_level_0', 'Player')": "Gary Gardner",
        "('Unnamed: 1_level_0', '#')": 20.0,
        "('Unnamed: 2_level_0', 'Nation')": "eng ENG",
        "('Unnamed: 3_level_0', 'Pos')": "CM,CB",
        "('Unnamed: 4_level_0', 'Age')": "27-094",
        "('Unnamed: 5_level_0', 'Min')": 90,
        "('Total', 'Cmp')": 31,
        "('Total', 'Att')": 44,
        "('Total', 'Cmp%')": 70.5,
        "('Total', 'TotDist')": 625,
        "('Total', 'PrgDist')": 193,
        "('Short', 'Cmp')": 9,
        "('Short', 'Att')": 14,
        "('Short', 'Cmp%')": 64.3,
        "('Medium', 'Cmp')": 17,
        "('Medium', 'Att')": 19,
        "('Medium', 'Cmp%')": 89.5,
        "('Long', 'Cmp')": 5,
        "('Long', 'Att')": 8,
        "('Long', 'Cmp%')": 62.5,
        "('Unnamed: 20_level_0', 'Ast')": 0,
        "('Unnamed: 21_level_0', 'xAG')": 0.0,
        "('Unnamed: 22_level_0', 'xA')": 0.0,
        "('Unnamed: 23_level_0', 'KP')": 0,
        "('Unnamed: 24_level_0', '1/3')": 4,
        "('Unnamed: 25_level_0', 'PPA')": 0,
        "('Unnamed: 26_level_0', 'CrsPA')": 0,
        "('Unnamed: 27_level_0', 'PrgP')": 5
    },
    {
        "('Unnamed: 0_level_0', 'Player')": "Daniel Crowley",
        "('Unnamed: 1_level_0', '#')": 7.0,
        "('Unnamed: 2_level_0', 'Nation')": "eng ENG",
        "('Unnamed: 3_level_0', 'Pos')": "RM",
        "('Unnamed: 4_level_0', 'Age')": "22-059",
        "('Unnamed: 5_level_0', 'Min')": 65,
        "('Total', 'Cmp')": 28,
        "('Total', 'Att')": 32,
        "('Total', 'Cmp%')": 87.5,
        "('Total', 'TotDist')": 465,
        "('Total', 'PrgDist')": 148,
        "('Short', 'Cmp')": 16,
        "('Short', 'Att')": 16,
        "('Short', 'Cmp%')": 100.0,
        "('Medium', 'Cmp')": 10,
        "('Medium', 'Att')": 11,
        "('Medium', 'Cmp%')": 90.9,
        "('Long', 'Cmp')": 2,
        "('Long', 'Att')": 4,
        "('Long', 'Cmp%')": 50.0,
        "('Unnamed: 20_level_0', 'Ast')": 0,
        "('Unnamed: 21_level_0', 'xAG')": 0.0,
        "('Unnamed: 22_level_0', 'xA')": 0.0,
        "('Unnamed: 23_level_0', 'KP')": 0,
        "('Unnamed: 24_level_0', '1/3')": 1,
        "('Unnamed: 25_level_0', 'PPA')": 1,
        "('Unnamed: 26_level_0', 'CrsPA')": 0,
        "('Unnamed: 27_level_0', 'PrgP')": 4
    },
    {
        "('Unnamed: 0_level_0', 'Player')": "Kerim Mrabti",
        "('Unnamed: 1_level_0', '#')": 18.0,
        "('Unnamed: 2_level_0', 'Nation')": "se SWE",
        "('Unnamed: 3_level_0', 'Pos')": "RM,CM",
        "('Unnamed: 4_level_0', 'Age')": "25-134",
        "('Unnamed: 5_level_0', 'Min')": 25,
        "('Total', 'Cmp')": 7,
        "('Total', 'Att')": 13,
        "('Total', 'Cmp%')": 53.8,
        "('Total', 'TotDist')": 129,
        "('Total', 'PrgDist')": 43,
        "('Short', 'Cmp')": 3,
        "('Short', 'Att')": 5,
        "('Short', 'Cmp%')": 60.0,
        "('Medium', 'Cmp')": 3,
        "('Medium', 'Att')": 5,
        "('Medium', 'Cmp%')": 60.0,
        "('Long', 'Cmp')": 1,
        "('Long', 'Att')": 3,
        "('Long', 'Cmp%')": 33.3,
        "('Unnamed: 20_level_0', 'Ast')": 0,
        "('Unnamed: 21_level_0', 'xAG')": 0.0,
        "('Unnamed: 22_level_0', 'xA')": 0.0,
        "('Unnamed: 23_level_0', 'KP')": 1,
        "('Unnamed: 24_level_0', '1/3')": 1,
        "('Unnamed: 25_level_0', 'PPA')": 0,
        "('Unnamed: 26_level_0', 'CrsPA')": 0,
        "('Unnamed: 27_level_0', 'PrgP')": 2
    },
    {
        "('Unnamed: 0_level_0', 'Player')": "Kristian Pedersen",
        "('Unnamed: 1_level_0', '#')": 3.0,
        "('Unnamed: 2_level_0', 'Nation')": "dk DEN",
        "('Unnamed: 3_level_0', 'Pos')": "LB,CB",
        "('Unnamed: 4_level_0', 'Age')": "25-058",
        "('Unnamed: 5_level_0', 'Min')": 90,
        "('Total', 'Cmp')": 45,
        "('Total', 'Att')": 61,
        "('Total', 'Cmp%')": 73.8,
        "('Total', 'TotDist')": 890,
        "('Total', 'PrgDist')": 523,
        "('Short', 'Cmp')": 19,
        "('Short', 'Att')": 20,
        "('Short', 'Cmp%')": 95.0,
        "('Medium', 'Cmp')": 18,
        "('Medium', 'Att')": 24,
        "('Medium', 'Cmp%')": 75.0,
        "('Long', 'Cmp')": 8,
        "('Long', 'Att')": 13,
        "('Long', 'Cmp%')": 61.5,
        "('Unnamed: 20_level_0', 'Ast')": 0,
        "('Unnamed: 21_level_0', 'xAG')": 0.1,
        "('Unnamed: 22_level_0', 'xA')": 0.1,
        "('Unnamed: 23_level_0', 'KP')": 2,
        "('Unnamed: 24_level_0', '1/3')": 6,
        "('Unnamed: 25_level_0', 'PPA')": 3,
        "('Unnamed: 26_level_0', 'CrsPA')": 1,
        "('Unnamed: 27_level_0', 'PrgP')": 8
    },
    {
        "('Unnamed: 0_level_0', 'Player')": "Jake Clarke-Salter",
        "('Unnamed: 1_level_0', '#')": 14.0,
        "('Unnamed: 2_level_0', 'Nation')": "eng ENG",
        "('Unnamed: 3_level_0', 'Pos')": "CB",
        "('Unnamed: 4_level_0', 'Age')": "22-009",
        "('Unnamed: 5_level_0', 'Min')": 82,
        "('Total', 'Cmp')": 25,
        "('Total', 'Att')": 27,
        "('Total', 'Cmp%')": 92.6,
        "('Total', 'TotDist')": 613,
        "('Total', 'PrgDist')": 308,
        "('Short', 'Cmp')": 5,
        "('Short', 'Att')": 5,
        "('Short', 'Cmp%')": 100.0,
        "('Medium', 'Cmp')": 13,
        "('Medium', 'Att')": 15,
        "('Medium', 'Cmp%')": 86.7,
        "('Long', 'Cmp')": 7,
        "('Long', 'Att')": 7,
        "('Long', 'Cmp%')": 100.0,
        "('Unnamed: 20_level_0', 'Ast')": 0,
        "('Unnamed: 21_level_0', 'xAG')": 0.0,
        "('Unnamed: 22_level_0', 'xA')": 0.0,
        "('Unnamed: 23_level_0', 'KP')": 0,
        "('Unnamed: 24_level_0', '1/3')": 2,
        "('Unnamed: 25_level_0', 'PPA')": 0,
        "('Unnamed: 26_level_0', 'CrsPA')": 0,
        "('Unnamed: 27_level_0', 'PrgP')": 1
    },
    {
        "('Unnamed: 0_level_0', 'Player')": "Jude Bellingham",
        "('Unnamed: 1_level_0', '#')": 22.0,
        "('Unnamed: 2_level_0', 'Nation')": "eng ENG",
        "('Unnamed: 3_level_0', 'Pos')": "CB,CM",
        "('Unnamed: 4_level_0', 'Age')": "16-094",
        "('Unnamed: 5_level_0', 'Min')": 8,
        "('Total', 'Cmp')": 3,
        "('Total', 'Att')": 5,
        "('Total', 'Cmp%')": 60.0,
        "('Total', 'TotDist')": 58,
        "('Total', 'PrgDist')": 23,
        "('Short', 'Cmp')": 1,
        "('Short', 'Att')": 2,
        "('Short', 'Cmp%')": 50.0,
        "('Medium', 'Cmp')": 2,
        "('Medium', 'Att')": 3,
        "('Medium', 'Cmp%')": 66.7,
        "('Long', 'Cmp')": 0,
        "('Long', 'Att')": 0,
        "('Long', 'Cmp%')": null,
        "('Unnamed: 20_level_0', 'Ast')": 0,
        "('Unnamed: 21_level_0', 'xAG')": 0.0,
        "('Unnamed: 22_level_0', 'xA')": 0.0,
        "('Unnamed: 23_level_0', 'KP')": 0,
        "('Unnamed: 24_level_0', '1/3')": 0,
        "('Unnamed: 25_level_0', 'PPA')": 1,
        "('Unnamed: 26_level_0', 'CrsPA')": 0,
        "('Unnamed: 27_level_0', 'PrgP')": 1
    },
    {
        "('Unnamed: 0_level_0', 'Player')": "Harlee Dean",
        "('Unnamed: 1_level_0', '#')": 12.0,
        "('Unnamed: 2_level_0', 'Nation')": "eng ENG",
        "('Unnamed: 3_level_0', 'Pos')": "CB",
        "('Unnamed: 4_level_0', 'Age')": "28-067",
        "('Unnamed: 5_level_0', 'Min')": 90,
        "('Total', 'Cmp')": 19,
        "('Total', 'Att')": 36,
        "('Total', 'Cmp%')": 52.8,
        "('Total', 'TotDist')": 439,
        "('Total', 'PrgDist')": 193,
        "('Short', 'Cmp')": 4,
        "('Short', 'Att')": 6,
        "('Short', 'Cmp%')": 66.7,
        "('Medium', 'Cmp')": 11,
        "('Medium', 'Att')": 15,
        "('Medium', 'Cmp%')": 73.3,
        "('Long', 'Cmp')": 4,
        "('Long', 'Att')": 14,
        "('Long', 'Cmp%')": 28.6,
        "('Unnamed: 20_level_0', 'Ast')": 0,
        "('Unnamed: 21_level_0', 'xAG')": 0.1,
        "('Unnamed: 22_level_0', 'xA')": 0.2,
        "('Unnamed: 23_level_0', 'KP')": 1,
        "('Unnamed: 24_level_0', '1/3')": 0,
        "('Unnamed: 25_level_0', 'PPA')": 0,
        "('Unnamed: 26_level_0', 'CrsPA')": 0,
        "('Unnamed: 27_level_0', 'PrgP')": 0
    },
    {
        "('Unnamed: 0_level_0', 'Player')": "Maxime Colin",
        "('Unnamed: 1_level_0', '#')": 5.0,
        "('Unnamed: 2_level_0', 'Nation')": "fr FRA",
        "('Unnamed: 3_level_0', 'Pos')": "RB,WB",
        "('Unnamed: 4_level_0', 'Age')": "27-320",
        "('Unnamed: 5_level_0', 'Min')": 90,
        "('Total', 'Cmp')": 54,
        "('Total', 'Att')": 68,
        "('Total', 'Cmp%')": 79.4,
        "('Total', 'TotDist')": 967,
        "('Total', 'PrgDist')": 312,
        "('Short', 'Cmp')": 27,
        "('Short', 'Att')": 30,
        "('Short', 'Cmp%')": 90.0,
        "('Medium', 'Cmp')": 20,
        "('Medium', 'Att')": 23,
        "('Medium', 'Cmp%')": 87.0,
        "('Long', 'Cmp')": 6,
        "('Long', 'Att')": 11,
        "('Long', 'Cmp%')": 54.5,
        "('Unnamed: 20_level_0', 'Ast')": 0,
        "('Unnamed: 21_level_0', 'xAG')": 0.1,
        "('Unnamed: 22_level_0', 'xA')": 0.1,
        "('Unnamed: 23_level_0', 'KP')": 2,
        "('Unnamed: 24_level_0', '1/3')": 6,
        "('Unnamed: 25_level_0', 'PPA')": 2,
        "('Unnamed: 26_level_0', 'CrsPA')": 1,
        "('Unnamed: 27_level_0', 'PrgP')": 7
    },
    {
        "('Unnamed: 0_level_0', 'Player')": "Lee Camp",
        "('Unnamed: 1_level_0', '#')": 1.0,
        "('Unnamed: 2_level_0', 'Nation')": "nir NIR",
        "('Unnamed: 3_level_0', 'Pos')": "GK",
        "('Unnamed: 4_level_0', 'Age')": "35-040",
        "('Unnamed: 5_level_0', 'Min')": 90,
        "('Total', 'Cmp')": 20,
        "('Total', 'Att')": 27,
        "('Total', 'Cmp%')": 74.1,
        "('Total', 'TotDist')": 1009,
        "('Total', 'PrgDist')": 919,
        "('Short', 'Cmp')": 0,
        "('Short', 'Att')": 0,
        "('Short', 'Cmp%')": null,
        "('Medium', 'Cmp')": 1,
        "('Medium', 'Att')": 1,
        "('Medium', 'Cmp%')": 100.0,
        "('Long', 'Cmp')": 19,
        "('Long', 'Att')": 26,
        "('Long', 'Cmp%')": 73.1,
        "('Unnamed: 20_level_0', 'Ast')": 0,
        "('Unnamed: 21_level_0', 'xAG')": 0.0,
        "('Unnamed: 22_level_0', 'xA')": 0.0,
        "('Unnamed: 23_level_0', 'KP')": 0,
        "('Unnamed: 24_level_0', '1/3')": 2,
        "('Unnamed: 25_level_0', 'PPA')": 0,
        "('Unnamed: 26_level_0', 'CrsPA')": 0,
        "('Unnamed: 27_level_0', 'PrgP')": 0
    },
    {
        "('Unnamed: 0_level_0', 'Player')": "14 Players",
        "('Unnamed: 1_level_0', '#')": null,
        "('Unnamed: 2_level_0', 'Nation')": null,
        "('Unnamed: 3_level_0', 'Pos')": null,
        "('Unnamed: 4_level_0', 'Age')": null,
        "('Unnamed: 5_level_0', 'Min')": 990,
        "('Total', 'Cmp')": 334,
        "('Total', 'Att')": 460,
        "('Total', 'Cmp%')": 72.6,
        "('Total', 'TotDist')": 6899,
        "('Total', 'PrgDist')": 3133,
        "('Short', 'Cmp')": 130,
        "('Short', 'Att')": 155,
        "('Short', 'Cmp%')": 83.9,
        "('Medium', 'Cmp')": 131,
        "('Medium', 'Att')": 167,
        "('Medium', 'Cmp%')": 78.4,
        "('Long', 'Cmp')": 65,
        "('Long', 'Att')": 109,
        "('Long', 'Cmp%')": 59.6,
        "('Unnamed: 20_level_0', 'Ast')": 0,
        "('Unnamed: 21_level_0', 'xAG')": 0.6,
        "('Unnamed: 22_level_0', 'xA')": 0.6,
        "('Unnamed: 23_level_0', 'KP')": 10,
        "('Unnamed: 24_level_0', '1/3')": 36,
        "('Unnamed: 25_level_0', 'PPA')": 8,
        "('Unnamed: 26_level_0', 'CrsPA')": 2,
        "('Unnamed: 27_level_0', 'PrgP')": 39
    }
]