[
    {
        "('Unnamed: 0_level_0', 'Minute')": "3",
        "('Unnamed: 1_level_0', 'Player')": "I\u00f1igo C\u00f3rdoba",
        "('Unnamed: 2_level_0', 'Squad')": "Athletic Club",
        "('Unnamed: 3_level_0', 'xG')": 0.3,
        "('Unnamed: 4_level_0', 'PSxG')": null,
        "('Unnamed: 5_level_0', 'Outcome')": "Off Target",
        "('Unnamed: 6_level_0', 'Distance')": 7.0,
        "('Unnamed: 7_level_0', 'Body Part')": "Head",
        "('Unnamed: 8_level_0', 'Notes')": null,
        "('SCA 1', 'Player')": "I\u00f1aki Williams",
        "('SCA 1', 'Event')": "Pass (Live)",
        "('SCA 2', 'Player')": "Iker Muniain",
        "('SCA 2', 'Event')": "Pass (Live)"
    },
    {
        "('Unnamed: 0_level_0', 'Minute')": "7",
        "('Unnamed: 1_level_0', 'Player')": "Yeray \u00c1lvarez",
        "('Unnamed: 2_level_0', 'Squad')": "Athletic Club",
        "('Unnamed: 3_level_0', 'xG')": 0.14,
        "('Unnamed: 4_level_0', 'PSxG')": null,
        "('Unnamed: 5_level_0', 'Outcome')": "Off Target",
        "('Unnamed: 6_level_0', 'Distance')": 9.0,
        "('Unnamed: 7_level_0', 'Body Part')": "Head",
        "('Unnamed: 8_level_0', 'Notes')": null,
        "('SCA 1', 'Player')": "Unai L\u00f3pez",
        "('SCA 1', 'Event')": "Pass (Dead)",
        "('SCA 2', 'Player')": "Iker Muniain",
        "('SCA 2', 'Event')": "Fouled"
    },
    {
        "('Unnamed: 0_level_0', 'Minute')": "10",
        "('Unnamed: 1_level_0', 'Player')": "Ra\u00fal Garc\u00eda",
        "('Unnamed: 2_level_0', 'Squad')": "Athletic Club",
        "('Unnamed: 3_level_0', 'xG')": 0.05,
        "('Unnamed: 4_level_0', 'PSxG')": 0.11,
        "('Unnamed: 5_level_0', 'Outcome')": "Saved",
        "('Unnamed: 6_level_0', 'Distance')": 14.0,
        "('Unnamed: 7_level_0', 'Body Part')": "Head",
        "('Unnamed: 8_level_0', 'Notes')": null,
        "('SCA 1', 'Player')": "I\u00f1aki Williams",
        "('SCA 1', 'Event')": "Pass (Live)",
        "('SCA 2', 'Player')": "Ander Capa",
        "('SCA 2', 'Event')": "Pass (Dead)"
    },
    {
        "('Unnamed: 0_level_0', 'Minute')": "15",
        "('Unnamed: 1_level_0', 'Player')": "Ra\u00fal Garc\u00eda",
        "('Unnamed: 2_level_0', 'Squad')": "Athletic Club",
        "('Unnamed: 3_level_0', 'xG')": 0.07,
        "('Unnamed: 4_level_0', 'PSxG')": 0.37,
        "('Unnamed: 5_level_0', 'Outcome')": "Saved",
        "('Unnamed: 6_level_0', 'Distance')": 18.0,
        "('Unnamed: 7_level_0', 'Body Part')": "Right Foot",
        "('Unnamed: 8_level_0', 'Notes')": null,
        "('SCA 1', 'Player')": "Iker Muniain",
        "('SCA 1', 'Event')": "Pass (Live)",
        "('SCA 2', 'Player')": null,
        "('SCA 2', 'Event')": null
    },
    {
        "('Unnamed: 0_level_0', 'Minute')": "16",
        "('Unnamed: 1_level_0', 'Player')": "Unai L\u00f3pez",
        "('Unnamed: 2_level_0', 'Squad')": "Athletic Club",
        "('Unnamed: 3_level_0', 'xG')": 0.03,
        "('Unnamed: 4_level_0', 'PSxG')": null,
        "('Unnamed: 5_level_0', 'Outcome')": "Blocked",
        "('Unnamed: 6_level_0', 'Distance')": 22.0,
        "('Unnamed: 7_level_0', 'Body Part')": "Right Foot",
        "('Unnamed: 8_level_0', 'Notes')": null,
        "('SCA 1', 'Player')": "Iker Muniain",
        "('SCA 1', 'Event')": "Pass (Live)",
        "('SCA 2', 'Player')": "Unai L\u00f3pez",
        "('SCA 2', 'Event')": "Pass (Live)"
    },
    {
        "('Unnamed: 0_level_0', 'Minute')": "28",
        "('Unnamed: 1_level_0', 'Player')": "Ander Capa",
        "('Unnamed: 2_level_0', 'Squad')": "Athletic Club",
        "('Unnamed: 3_level_0', 'xG')": 0.07,
        "('Unnamed: 4_level_0', 'PSxG')": null,
        "('Unnamed: 5_level_0', 'Outcome')": "Blocked",
        "('Unnamed: 6_level_0', 'Distance')": 12.0,
        "('Unnamed: 7_level_0', 'Body Part')": "Right Foot",
        "('Unnamed: 8_level_0', 'Notes')": null,
        "('SCA 1', 'Player')": "I\u00f1aki Williams",
        "('SCA 1', 'Event')": "Pass (Live)",
        "('SCA 2', 'Player')": "Iker Muniain",
        "('SCA 2', 'Event')": "Pass (Live)"
    },
    {
        "('Unnamed: 0_level_0', 'Minute')": "29",
        "('Unnamed: 1_level_0', 'Player')": "Unai L\u00f3pez",
        "('Unnamed: 2_level_0', 'Squad')": "Athletic Club",
        "('Unnamed: 3_level_0', 'xG')": 0.02,
        "('Unnamed: 4_level_0', 'PSxG')": null,
        "('Unnamed: 5_level_0', 'Outcome')": "Off Target",
        "('Unnamed: 6_level_0', 'Distance')": 31.0,
        "('Unnamed: 7_level_0', 'Body Part')": "Right Foot",
        "('Unnamed: 8_level_0', 'Notes')": null,
        "('SCA 1', 'Player')": "Ra\u00fal Garc\u00eda",
        "('SCA 1', 'Event')": "Pass (Live)",
        "('SCA 2', 'Player')": "I\u00f1igo C\u00f3rdoba",
        "('SCA 2', 'Event')": "Pass (Live)"
    },
    {
        "('Unnamed: 0_level_0', 'Minute')": "33",
        "('Unnamed: 1_level_0', 'Player')": "I\u00f1aki Williams",
        "('Unnamed: 2_level_0', 'Squad')": "Athletic Club",
        "('Unnamed: 3_level_0', 'xG')": 0.25,
        "('Unnamed: 4_level_0', 'PSxG')": 0.18,
        "('Unnamed: 5_level_0', 'Outcome')": "Goal",
        "('Unnamed: 6_level_0', 'Distance')": 10.0,
        "('Unnamed: 7_level_0', 'Body Part')": "Right Foot",
        "('Unnamed: 8_level_0', 'Notes')": "Deflected",
        "('SCA 1', 'Player')": "I\u00f1aki Williams",
        "('SCA 1', 'Event')": "Take-On",
        "('SCA 2', 'Player')": "I\u00f1aki Williams",
        "('SCA 2', 'Event')": "Take-On"
    },
    {
        "('Unnamed: 0_level_0', 'Minute')": null,
        "('Unnamed: 1_level_0', 'Player')": null,
        "('Unnamed: 2_level_0', 'Squad')": null,
        "('Unnamed: 3_level_0', 'xG')": null,
        "('Unnamed: 4_level_0', 'PSxG')": null,
        "('Unnamed: 5_level_0', 'Outcome')": null,
        "('Unnamed: 6_level_0', 'Distance')": null,
        "('Unnamed: 7_level_0', 'Body Part')": null,
        "('Unnamed: 8_level_0', 'Notes')": null,
        "('SCA 1', 'Player')": null,
        "('SCA 1', 'Event')": null,
        "('SCA 2', 'Player')": null,
        "('SCA 2', 'Event')": null
    },
    {
        "('Unnamed: 0_level_0', 'Minute')": "50",
        "('Unnamed: 1_level_0', 'Player')": "Unai L\u00f3pez",
        "('Unnamed: 2_level_0', 'Squad')": "Athletic Club",
        "('Unnamed: 3_level_0', 'xG')": 0.03,
        "('Unnamed: 4_level_0', 'PSxG')": null,
        "('Unnamed: 5_level_0', 'Outcome')": "Off Target",
        "('Unnamed: 6_level_0', 'Distance')": 27.0,
        "('Unnamed: 7_level_0', 'Body Part')": "Right Foot",
        "('Unnamed: 8_level_0', 'Notes')": null,
        "('SCA 1', 'Player')": "Iker Muniain",
        "('SCA 1', 'Event')": "Pass (Live)",
        "('SCA 2', 'Player')": "Ander Capa",
        "('SCA 2', 'Event')": "Pass (Live)"
    },
    {
        "('Unnamed: 0_level_0', 'Minute')": "57",
        "('Unnamed: 1_level_0', 'Player')": "Iker Muniain",
        "('Unnamed: 2_level_0', 'Squad')": "Athletic Club",
        "('Unnamed: 3_level_0', 'xG')": 0.03,
        "('Unnamed: 4_level_0', 'PSxG')": 0.08,
        "('Unnamed: 5_level_0', 'Outcome')": "Saved",
        "('Unnamed: 6_level_0', 'Distance')": 29.0,
        "('Unnamed: 7_level_0', 'Body Part')": "Right Foot",
        "('Unnamed: 8_level_0', 'Notes')": null,
        "('SCA 1', 'Player')": "Dani Garc\u00eda",
        "('SCA 1', 'Event')": "Pass (Live)",
        "('SCA 2', 'Player')": "I\u00f1igo C\u00f3rdoba",
        "('SCA 2', 'Event')": "Pass (Live)"
    },
    {
        "('Unnamed: 0_level_0', 'Minute')": "64",
        "('Unnamed: 1_level_0', 'Player')": "Unai L\u00f3pez",
        "('Unnamed: 2_level_0', 'Squad')": "Athletic Club",
        "('Unnamed: 3_level_0', 'xG')": 0.05,
        "('Unnamed: 4_level_0', 'PSxG')": null,
        "('Unnamed: 5_level_0', 'Outcome')": "Off Target",
        "('Unnamed: 6_level_0', 'Distance')": 20.0,
        "('Unnamed: 7_level_0', 'Body Part')": "Right Foot",
        "('Unnamed: 8_level_0', 'Notes')": null,
        "('SCA 1', 'Player')": "Iker Muniain",
        "('SCA 1', 'Event')": "Pass (Live)",
        "('SCA 2', 'Player')": "Iker Muniain",
        "('SCA 2', 'Event')": "Take-On"
    },
    {
        "('Unnamed: 0_level_0', 'Minute')": "67",
        "('Unnamed: 1_level_0', 'Player')": "Ander Capa",
        "('Unnamed: 2_level_0', 'Squad')": "Athletic Club",
        "('Unnamed: 3_level_0', 'xG')": 0.02,
        "('Unnamed: 4_level_0', 'PSxG')": null,
        "('Unnamed: 5_level_0', 'Outcome')": "Blocked",
        "('Unnamed: 6_level_0', 'Distance')": 22.0,
        "('Unnamed: 7_level_0', 'Body Part')": "Right Foot",
        "('Unnamed: 8_level_0', 'Notes')": null,
        "('SCA 1', 'Player')": "Ander Capa",
        "('SCA 1', 'Event')": "Pass (Live)",
        "('SCA 2', 'Player')": "Dani Garc\u00eda",
        "('SCA 2', 'Event')": "Pass (Live)"
    },
    {
        "('Unnamed: 0_level_0', 'Minute')": "73",
        "('Unnamed: 1_level_0', 'Player')": "I\u00f1igo Mart\u00ednez",
        "('Unnamed: 2_level_0', 'Squad')": "Athletic Club",
        "('Unnamed: 3_level_0', 'xG')": 0.04,
        "('Unnamed: 4_level_0', 'PSxG')": null,
        "('Unnamed: 5_level_0', 'Outcome')": "Blocked",
        "('Unnamed: 6_level_0', 'Distance')": 25.0,
        "('Unnamed: 7_level_0', 'Body Part')": "Left Foot",
        "('Unnamed: 8_level_0', 'Notes')": null,
        "('SCA 1', 'Player')": "I\u00f1igo Mart\u00ednez",
        "('SCA 1', 'Event')": "Take-On",
        "('SCA 2', 'Player')": "Iker Muniain",
        "('SCA 2', 'Event')": "Pass (Live)"
    },
    {
        "('Unnamed: 0_level_0', 'Minute')": "76",
        "('Unnamed: 1_level_0', 'Player')": "Ra\u00fal Garc\u00eda",
        "('Unnamed: 2_level_0', 'Squad')": "Athletic Club",
        "('Unnamed: 3_level_0', 'xG')": 0.15,
        "('Unnamed: 4_level_0', 'PSxG')": null,
        "('Unnamed: 5_level_0', 'Outcome')": "Off Target",
        "('Unnamed: 6_level_0', 'Distance')": 11.0,
        "('Unnamed: 7_level_0', 'Body Part')": "Other",
        "('Unnamed: 8_level_0', 'Notes')": null,
        "('SCA 1', 'Player')": "Be\u00f1at Etxebarria",
        "('SCA 1', 'Event')": "Pass (Dead)",
        "('SCA 2', 'Player')": "Iker Muniain",
        "('SCA 2', 'Event')": "Fouled"
    },
    {
        "('Unnamed: 0_level_0', 'Minute')": "80",
        "('Unnamed: 1_level_0', 'Player')": "I\u00f1aki Williams",
        "('Unnamed: 2_level_0', 'Squad')": "Athletic Club",
        "('Unnamed: 3_level_0', 'xG')": 0.1,
        "('Unnamed: 4_level_0', 'PSxG')": null,
        "('Unnamed: 5_level_0', 'Outcome')": "Blocked",
        "('Unnamed: 6_level_0', 'Distance')": 11.0,
        "('Unnamed: 7_level_0', 'Body Part')": "Left Foot",
        "('Unnamed: 8_level_0', 'Notes')": null,
        "('SCA 1', 'Player')": "I\u00f1aki Williams",
        "('SCA 1', 'Event')": "Take-On",
        "('SCA 2', 'Player')": "I\u00f1aki Williams",
        "('SCA 2', 'Event')": "Take-On"
    },
    {
        "('Unnamed: 0_level_0', 'Minute')": "87",
        "('Unnamed: 1_level_0', 'Player')": "Larra",
        "('Unnamed: 2_level_0', 'Squad')": "Athletic Club",
        "('Unnamed: 3_level_0', 'xG')": 0.02,
        "('Unnamed: 4_level_0', 'PSxG')": 0.04,
        "('Unnamed: 5_level_0', 'Outcome')": "Saved",
        "('Unnamed: 6_level_0', 'Distance')": 24.0,
        "('Unnamed: 7_level_0', 'Body Part')": "Right Foot",
        "('Unnamed: 8_level_0', 'Notes')": null,
        "('SCA 1', 'Player')": "Be\u00f1at Etxebarria",
        "('SCA 1', 'Event')": "Pass (Live)",
        "('SCA 2', 'Player')": "I\u00f1igo Mart\u00ednez",
        "('SCA 2', 'Event')": "Pass (Live)"
    },
    {
        "('Unnamed: 0_level_0', 'Minute')": "88",
        "('Unnamed: 1_level_0', 'Player')": "Iker Muniain",
        "('Unnamed: 2_level_0', 'Squad')": "Athletic Club",
        "('Unnamed: 3_level_0', 'xG')": 0.1,
        "('Unnamed: 4_level_0', 'PSxG')": 0.51,
        "('Unnamed: 5_level_0', 'Outcome')": "Saved",
        "('Unnamed: 6_level_0', 'Distance')": 21.0,
        "('Unnamed: 7_level_0', 'Body Part')": "Right Foot",
        "('Unnamed: 8_level_0', 'Notes')": null,
        "('SCA 1', 'Player')": "Iker Muniain",
        "('SCA 1', 'Event')": "Take-On",
        "('SCA 2', 'Player')": "Iker Muniain",
        "('SCA 2', 'Event')": "Take-On"
    },
    {
        "('Unnamed: 0_level_0', 'Minute')": "89",
        "('Unnamed: 1_level_0', 'Player')": "Larra",
        "('Unnamed: 2_level_0', 'Squad')": "Athletic Club",
        "('Unnamed: 3_level_0', 'xG')": 0.03,
        "('Unnamed: 4_level_0', 'PSxG')": null,
        "('Unnamed: 5_level_0', 'Outcome')": "Blocked",
        "('Unnamed: 6_level_0', 'Distance')": 22.0,
        "('Unnamed: 7_level_0', 'Body Part')": "Right Foot",
        "('Unnamed: 8_level_0', 'Notes')": null,
        "('SCA 1', 'Player')": "Iker Muniain",
        "('SCA 1', 'Event')": "Shot",
        "('SCA 2', 'Player')": null,
        "('SCA 2', 'Event')": null
    },
    {
        "('Unnamed: 0_level_0', 'Minute')": "90+3",
        "('Unnamed: 1_level_0', 'Player')": "Be\u00f1at Etxebarria",
        "('Unnamed: 2_level_0', 'Squad')": "Athletic Club",
        "('Unnamed: 3_level_0', 'xG')": 0.04,
        "('Unnamed: 4_level_0', 'PSxG')": 0.2,
        "('Unnamed: 5_level_0', 'Outcome')": "Saved",
        "('Unnamed: 6_level_0', 'Distance')": 17.0,
        "('Unnamed: 7_level_0', 'Body Part')": "Head",
        "('Unnamed: 8_level_0', 'Notes')": null,
        "('SCA 1', 'Player')": "Ander Capa",
        "('SCA 1', 'Event')": "Pass (Live)",
        "('SCA 2', 'Player')": "Yeray \u00c1lvarez",
        "('SCA 2', 'Event')": "Pass (Live)"
    }
]