[
    {
        "('Unnamed: 0_level_0', 'Player')": "Thibaut Courtois",
        "('Unnamed: 1_level_0', 'Nation')": "be BEL",
        "('Unnamed: 2_level_0', 'Age')": "28-034",
        "('Unnamed: 3_level_0', 'Min')": 90,
        "('Shot Stopping', 'SoTA')": 5,
        "('Shot Stopping', 'GA')": 1,
        "('Shot Stopping', 'Saves')": 4,
        "('Shot Stopping', 'Save%')": 80.0,
        "('Shot Stopping', 'PSxG')": 1.1,
        "('Launched', 'Cmp')": 2,
        "('Launched', 'Att')": 13,
        "('Launched', 'Cmp%')": 15.4,
        "('Passes', 'Att (GK)')": 39,
        "('Passes', 'Thr')": 7,
        "('Passes', 'Launch%')": 28.2,
        "('Passes', 'AvgLen')": 29.7,
        "('Goal Kicks', 'Att')": 10,
        "('Goal Kicks', 'Launch%')": 20.0,
        "('Goal Kicks', 'AvgLen')": 27.6,
        "('Crosses', 'Opp')": 15,
        "('Crosses', 'Stp')": 0,
        "('Crosses', 'Stp%')": 0.0,
        "('Sweeper', '#OPA')": 0,
        "('Sweeper', 'AvgDist')": 7.4
    }
]