[
    {
        "('Unnamed: 0_level_0', 'Player')": "Marco Bizot",
        "('Unnamed: 1_level_0', 'Nation')": "nl NED",
        "('Unnamed: 2_level_0', 'Age')": "31-065",
        "('Unnamed: 3_level_0', 'Min')": 90,
        "('Shot Stopping', 'SoTA')": 8,
        "('Shot Stopping', 'GA')": 4,
        "('Shot Stopping', 'Saves')": 4,
        "('Shot Stopping', 'Save%')": 62.5,
        "('Shot Stopping', 'PSxG')": 3.7,
        "('Launched', 'Cmp')": 7,
        "('Launched', 'Att')": 17,
        "('Launched', 'Cmp%')": 41.2,
        "('Passes', 'Att (GK)')": 20,
        "('Passes', 'Thr')": 3,
        "('Passes', 'Launch%')": 40.0,
        "('Passes', 'AvgLen')": 32.8,
        "('Goal Kicks', 'Att')": 12,
        "('Goal Kicks', 'Launch%')": 75.0,
        "('Goal Kicks', 'AvgLen')": 49.8,
        "('Crosses', 'Opp')": 20,
        "('Crosses', 'Stp')": 2,
        "('Crosses', 'Stp%')": 10.0,
        "('Sweeper', '#OPA')": 0,
        "('Sweeper', 'AvgDist')": 7.0
    }
]