[
    {
        "Date": "2017-08-04",
        "Time": "19:45",
        "Comp": "Championship",
        "Round": "Matchweek 1",
        "Day": "Fri",
        "Venue": "Away",
        "Result": "L",
        "GF": 0,
        "GA": 1,
        "Opponent": "Nott'ham Forest",
        "Poss": 32,
        "Attendance": 28065,
        "Captain": "Steve Morison",
        "Formation": "4-4-2",
        "Referee": "Peter Bankes",
        "Match Report": "Match Report",
        "Notes": null
    },
    {
        "Date": "2017-08-08",
        "Time": "19:45",
        "Comp": "EFL Cup",
        "Round": "First round",
        "Day": "Tue",
        "Venue": "Home",
        "Result": "W",
        "GF": 2,
        "GA": 0,
        "Opponent": "Stevenage",
        "Poss": 55,
        "Attendance": 3096,
        "Captain": "Tony Craig",
        "Formation": "4-4-2",
        "Referee": "Simon Hooper",
        "Match Report": "Match Report",
        "Notes": null
    },
    {
        "Date": "2017-08-12",
        "Time": "15:00",
        "Comp": "Championship",
        "Round": "Matchweek 2",
        "Day": "Sat",
        "Venue": "Home",
        "Result": "D",
        "GF": 1,
        "GA": 1,
        "Opponent": "Bolton",
        "Poss": 53,
        "Attendance": 12238,
        "Captain": "Steve Morison",
        "Formation": "4-4-2",
        "Referee": "Andrew Davies",
        "Match Report": "Match Report",
        "Notes": null
    },
    {
        "Date": "2017-08-15",
        "Time": "19:45",
        "Comp": "Championship",
        "Round": "Matchweek 3",
        "Day": "Tue",
        "Venue": "Home",
        "Result": "L",
        "GF": 3,
        "GA": 4,
        "Opponent": "Ipswich Town",
        "Poss": 56,
        "Attendance": 11919,
        "Captain": "Steve Morison",
        "Formation": "4-4-2",
        "Referee": "James Linington",
        "Match Report": "Match Report",
        "Notes": null
    },
    {
        "Date": "2017-08-19",
        "Time": "15:00",
        "Comp": "Championship",
        "Round": "Matchweek 4",
        "Day": "Sat",
        "Venue": "Away",
        "Result": "D",
        "GF": 0,
        "GA": 0,
        "Opponent": "Bristol City",
        "Poss": 41,
        "Attendance": 18230,
        "Captain": "Steve Morison",
        "Formation": "4-4-2",
        "Referee": "Darren England",
        "Match Report": "Match Report",
        "Notes": null
    },
    {
        "Date": "2017-08-22",
        "Time": "20:00",
        "Comp": "EFL Cup",
        "Round": "Second round",
        "Day": "Tue",
        "Venue": "Away",
        "Result": "L",
        "GF": 1,
        "GA": 3,
        "Opponent": "Reading",
        "Poss": 37,
        "Attendance": 7148,
        "Captain": "Tony Craig",
        "Formation": "4-4-2",
        "Referee": "Charles Breakspear",
        "Match Report": "Match Report",
        "Notes": "Required Extra Time"
    },
    {
        "Date": "2017-08-26",
        "Time": "15:00",
        "Comp": "Championship",
        "Round": "Matchweek 5",
        "Day": "Sat",
        "Venue": "Home",
        "Result": "W",
        "GF": 4,
        "GA": 0,
        "Opponent": "Norwich City",
        "Poss": 28,
        "Attendance": 12671,
        "Captain": "Steve Morison",
        "Formation": "4-4-2",
        "Referee": "Tony Harrington",
        "Match Report": "Match Report",
        "Notes": null
    },
    {
        "Date": "2017-09-09",
        "Time": "15:00",
        "Comp": "Championship",
        "Round": "Matchweek 6",
        "Day": "Sat",
        "Venue": "Away",
        "Result": "L",
        "GF": 0,
        "GA": 1,
        "Opponent": "Wolves",
        "Poss": 33,
        "Attendance": 24426,
        "Captain": "Steve Morison",
        "Formation": "4-4-2",
        "Referee": "Robert Madley",
        "Match Report": "Match Report",
        "Notes": null
    },
    {
        "Date": "2017-09-12",
        "Time": "19:45",
        "Comp": "Championship",
        "Round": "Matchweek 7",
        "Day": "Tue",
        "Venue": "Away",
        "Result": "D",
        "GF": 2,
        "GA": 2,
        "Opponent": "QPR",
        "Poss": 31,
        "Attendance": 12600,
        "Captain": "Steve Morison",
        "Formation": "4-4-2",
        "Referee": "Roger East",
        "Match Report": "Match Report",
        "Notes": null
    },
    {
        "Date": "2017-09-16",
        "Time": "15:00",
        "Comp": "Championship",
        "Round": "Matchweek 8",
        "Day": "Sat",
        "Venue": "Home",
        "Result": "W",
        "GF": 1,
        "GA": 0,
        "Opponent": "Leeds United",
        "Poss": 46,
        "Attendance": 16447,
        "Captain": "Steve Morison",
        "Formation": "4-4-2",
        "Referee": "Tim Robinson",
        "Match Report": "Match Report",
        "Notes": null
    },
    {
        "Date": "2017-09-23",
        "Time": "15:00",
        "Comp": "Championship",
        "Round": "Matchweek 9",
        "Day": "Sat",
        "Venue": "Away",
        "Result": "D",
        "GF": 0,
        "GA": 0,
        "Opponent": "Preston",
        "Poss": 39,
        "Attendance": 12363,
        "Captain": "Steve Morison",
        "Formation": "4-4-2",
        "Referee": "Darren Bond",
        "Match Report": "Match Report",
        "Notes": null
    },
    {
        "Date": "2017-09-26",
        "Time": "19:45",
        "Comp": "Championship",
        "Round": "Matchweek 10",
        "Day": "Tue",
        "Venue": "Home",
        "Result": "W",
        "GF": 2,
        "GA": 1,
        "Opponent": "Reading",
        "Poss": 34,
        "Attendance": 10399,
        "Captain": "Steve Morison",
        "Formation": "4-4-2",
        "Referee": "Andy Madley",
        "Match Report": "Match Report",
        "Notes": null
    },
    {
        "Date": "2017-09-30",
        "Time": "15:00",
        "Comp": "Championship",
        "Round": "Matchweek 11",
        "Day": "Sat",
        "Venue": "Home",
        "Result": "L",
        "GF": 1,
        "GA": 3,
        "Opponent": "Barnsley",
        "Poss": 50,
        "Attendance": 12147,
        "Captain": "Steve Morison",
        "Formation": "4-4-2",
        "Referee": "Oliver Langford",
        "Match Report": "Match Report",
        "Notes": null
    },
    {
        "Date": "2017-10-14",
        "Time": "15:00",
        "Comp": "Championship",
        "Round": "Matchweek 12",
        "Day": "Sat",
        "Venue": "Away",
        "Result": "L",
        "GF": 0,
        "GA": 1,
        "Opponent": "Brentford",
        "Poss": 37,
        "Attendance": 9622,
        "Captain": "Shaun Hutchinson",
        "Formation": "4-4-2",
        "Referee": "Lee Probert",
        "Match Report": "Match Report",
        "Notes": null
    },
    {
        "Date": "2017-10-21",
        "Time": "17:30",
        "Comp": "Championship",
        "Round": "Matchweek 13",
        "Day": "Sat",
        "Venue": "Home",
        "Result": "W",
        "GF": 2,
        "GA": 0,
        "Opponent": "Birmingham City",
        "Poss": 50,
        "Attendance": 14500,
        "Captain": "Steve Morison",
        "Formation": "4-4-2",
        "Referee": "Simon Hooper",
        "Match Report": "Match Report",
        "Notes": null
    },
    {
        "Date": "2017-10-28",
        "Time": "15:00",
        "Comp": "Championship",
        "Round": "Matchweek 14",
        "Day": "Sat",
        "Venue": "Away",
        "Result": "D",
        "GF": 0,
        "GA": 0,
        "Opponent": "Cardiff City",
        "Poss": 43,
        "Attendance": 18496,
        "Captain": "Steve Morison",
        "Formation": "4-4-2",
        "Referee": "Steve Martin",
        "Match Report": "Match Report",
        "Notes": null
    },
    {
        "Date": "2017-10-31",
        "Time": "19:45",
        "Comp": "Championship",
        "Round": "Matchweek 15",
        "Day": "Tue",
        "Venue": "Away",
        "Result": "L",
        "GF": 1,
        "GA": 2,
        "Opponent": "Sheffield Weds",
        "Poss": 40,
        "Attendance": 23403,
        "Captain": "Shaun Hutchinson",
        "Formation": "4-4-2",
        "Referee": "James Linington",
        "Match Report": "Match Report",
        "Notes": null
    },
    {
        "Date": "2017-11-04",
        "Time": "15:00",
        "Comp": "Championship",
        "Round": "Matchweek 16",
        "Day": "Sat",
        "Venue": "Home",
        "Result": "L",
        "GF": 0,
        "GA": 1,
        "Opponent": "Burton Albion",
        "Poss": 53,
        "Attendance": 11507,
        "Captain": "Tony Craig",
        "Formation": "4-4-2",
        "Referee": "Tony Harrington",
        "Match Report": "Match Report",
        "Notes": null
    },
    {
        "Date": "2017-11-18",
        "Time": "15:00",
        "Comp": "Championship",
        "Round": "Matchweek 17",
        "Day": "Sat",
        "Venue": "Away",
        "Result": "D",
        "GF": 2,
        "GA": 2,
        "Opponent": "Sunderland",
        "Poss": 35,
        "Attendance": 27399,
        "Captain": "Shaun Hutchinson",
        "Formation": "4-4-2",
        "Referee": "Tim Robinson",
        "Match Report": "Match Report",
        "Notes": null
    },
    {
        "Date": "2017-11-21",
        "Time": "19:45",
        "Comp": "Championship",
        "Round": "Matchweek 18",
        "Day": "Tue",
        "Venue": "Home",
        "Result": "D",
        "GF": 0,
        "GA": 0,
        "Opponent": "Hull City",
        "Poss": 48,
        "Attendance": 9817,
        "Captain": "Shaun Hutchinson",
        "Formation": "4-4-2",
        "Referee": "Jeremy Simpson",
        "Match Report": "Match Report",
        "Notes": null
    },
    {
        "Date": "2017-11-25",
        "Time": "15:00",
        "Comp": "Championship",
        "Round": "Matchweek 19",
        "Day": "Sat",
        "Venue": "Away",
        "Result": "L",
        "GF": 0,
        "GA": 1,
        "Opponent": "Fulham",
        "Poss": 36,
        "Attendance": 17984,
        "Captain": "Steve Morison",
        "Formation": "4-4-2",
        "Referee": "Paul Tierney",
        "Match Report": "Match Report",
        "Notes": null
    },
    {
        "Date": "2017-12-02",
        "Time": "15:00",
        "Comp": "Championship",
        "Round": "Matchweek 20",
        "Day": "Sat",
        "Venue": "Home",
        "Result": "W",
        "GF": 3,
        "GA": 1,
        "Opponent": "Sheffield Utd",
        "Poss": 37,
        "Attendance": 12669,
        "Captain": "Steve Morison",
        "Formation": "4-4-2",
        "Referee": "Andy Madley",
        "Match Report": "Match Report",
        "Notes": null
    },
    {
        "Date": "2017-12-09",
        "Time": "15:00",
        "Comp": "Championship",
        "Round": "Matchweek 21",
        "Day": "Sat",
        "Venue": "Away",
        "Result": "D",
        "GF": 0,
        "GA": 0,
        "Opponent": "Aston Villa",
        "Poss": 44,
        "Attendance": 29628,
        "Captain": "Steve Morison",
        "Formation": "4-4-2",
        "Referee": "Andrew Davies",
        "Match Report": "Match Report",
        "Notes": null
    },
    {
        "Date": "2017-12-16",
        "Time": "15:00",
        "Comp": "Championship",
        "Round": "Matchweek 22",
        "Day": "Sat",
        "Venue": "Home",
        "Result": "W",
        "GF": 2,
        "GA": 1,
        "Opponent": "Middlesbrough",
        "Poss": 34,
        "Attendance": 12026,
        "Captain": "Steve Morison",
        "Formation": "4-4-2",
        "Referee": "Oliver Langford",
        "Match Report": "Match Report",
        "Notes": null
    },
    {
        "Date": "2017-12-23",
        "Time": "15:00",
        "Comp": "Championship",
        "Round": "Matchweek 23",
        "Day": "Sat",
        "Venue": "Away",
        "Result": "L",
        "GF": 0,
        "GA": 3,
        "Opponent": "Derby County",
        "Poss": 48,
        "Attendance": 25813,
        "Captain": "Steve Morison",
        "Formation": "4-4-2",
        "Referee": "Darren England",
        "Match Report": "Match Report",
        "Notes": null
    },
    {
        "Date": "2017-12-26",
        "Time": "13:00",
        "Comp": "Championship",
        "Round": "Matchweek 24",
        "Day": "Tue",
        "Venue": "Home",
        "Result": "D",
        "GF": 2,
        "GA": 2,
        "Opponent": "Wolves",
        "Poss": 37,
        "Attendance": 13121,
        "Captain": "Shaun Williams",
        "Formation": "4-4-2",
        "Referee": "Tim Robinson",
        "Match Report": "Match Report",
        "Notes": null
    },
    {
        "Date": "2017-12-29",
        "Time": "19:45",
        "Comp": "Championship",
        "Round": "Matchweek 25",
        "Day": "Fri",
        "Venue": "Home",
        "Result": "W",
        "GF": 1,
        "GA": 0,
        "Opponent": "QPR",
        "Poss": 54,
        "Attendance": 16601,
        "Captain": "Steve Morison",
        "Formation": "4-4-2",
        "Referee": "Keith Stroud",
        "Match Report": "Match Report",
        "Notes": null
    },
    {
        "Date": "2018-01-01",
        "Time": "15:00",
        "Comp": "Championship",
        "Round": "Matchweek 26",
        "Day": "Mon",
        "Venue": "Away",
        "Result": "L",
        "GF": 1,
        "GA": 2,
        "Opponent": "Norwich City",
        "Poss": 39,
        "Attendance": 25774,
        "Captain": "Steve Morison",
        "Formation": "4-4-2",
        "Referee": "Steve Martin",
        "Match Report": "Match Report",
        "Notes": null
    },
    {
        "Date": "2018-01-06",
        "Time": "15:00",
        "Comp": "FA Cup",
        "Round": "Third round",
        "Day": "Sat",
        "Venue": "Home",
        "Result": "W",
        "GF": 4,
        "GA": 1,
        "Opponent": "Barnsley",
        "Poss": 49,
        "Attendance": 5319,
        "Captain": "Tony Craig",
        "Formation": "4-4-2",
        "Referee": "Darren Bond",
        "Match Report": "Match Report",
        "Notes": null
    },
    {
        "Date": "2018-01-13",
        "Time": "15:00",
        "Comp": "Championship",
        "Round": "Matchweek 27",
        "Day": "Sat",
        "Venue": "Home",
        "Result": "D",
        "GF": 1,
        "GA": 1,
        "Opponent": "Preston",
        "Poss": 39,
        "Attendance": 11751,
        "Captain": "Steve Morison",
        "Formation": "4-4-2",
        "Referee": "Jeremy Simpson",
        "Match Report": "Match Report",
        "Notes": null
    },
    {
        "Date": "2018-01-20",
        "Time": "15:00",
        "Comp": "Championship",
        "Round": "Matchweek 28",
        "Day": "Sat",
        "Venue": "Away",
        "Result": "W",
        "GF": 4,
        "GA": 3,
        "Opponent": "Leeds United",
        "Poss": 51,
        "Attendance": 33564,
        "Captain": "Steve Morison",
        "Formation": "4-4-2",
        "Referee": "David Coote",
        "Match Report": "Match Report",
        "Notes": null
    },
    {
        "Date": "2018-01-27",
        "Time": "15:00",
        "Comp": "FA Cup",
        "Round": "Fourth round",
        "Day": "Sat",
        "Venue": "Home",
        "Result": "D",
        "GF": 2,
        "GA": 2,
        "Opponent": "Rochdale",
        "Poss": 45,
        "Attendance": 8346,
        "Captain": "Tony Craig",
        "Formation": "4-4-2",
        "Referee": "Andy Madley",
        "Match Report": "Match Report",
        "Notes": null
    },
    {
        "Date": "2018-01-30",
        "Time": "19:45",
        "Comp": "Championship",
        "Round": "Matchweek 29",
        "Day": "Tue",
        "Venue": "Home",
        "Result": "D",
        "GF": 0,
        "GA": 0,
        "Opponent": "Derby County",
        "Poss": 41,
        "Attendance": 10931,
        "Captain": "Shaun Hutchinson",
        "Formation": "4-4-2",
        "Referee": "Oliver Langford",
        "Match Report": "Match Report",
        "Notes": null
    },
    {
        "Date": "2018-02-03",
        "Time": "15:00",
        "Comp": "Championship",
        "Round": "Matchweek 30",
        "Day": "Sat",
        "Venue": "Away",
        "Result": "W",
        "GF": 2,
        "GA": 0,
        "Opponent": "Reading",
        "Poss": 38,
        "Attendance": 17282,
        "Captain": "Steve Morison",
        "Formation": "4-4-2",
        "Referee": "Geoff Eltringham",
        "Match Report": "Match Report",
        "Notes": null
    },
    {
        "Date": "2018-02-06",
        "Time": "19:45",
        "Comp": "FA Cup",
        "Round": "Fourth round",
        "Day": "Tue",
        "Venue": "Away",
        "Result": "L",
        "GF": 0,
        "GA": 1,
        "Opponent": "Rochdale",
        "Poss": 43,
        "Attendance": 2790,
        "Captain": "Shaun Hutchinson",
        "Formation": "4-4-2",
        "Referee": "Tim Robinson",
        "Match Report": "Match Report",
        "Notes": null
    },
    {
        "Date": "2018-02-09",
        "Time": "19:45",
        "Comp": "Championship",
        "Round": "Matchweek 31",
        "Day": "Fri",
        "Venue": "Home",
        "Result": "D",
        "GF": 1,
        "GA": 1,
        "Opponent": "Cardiff City",
        "Poss": 56,
        "Attendance": 13204,
        "Captain": "Steve Morison",
        "Formation": "4-4-2",
        "Referee": "Keith Stroud",
        "Match Report": "Match Report",
        "Notes": null
    },
    {
        "Date": "2018-02-17",
        "Time": "15:00",
        "Comp": "Championship",
        "Round": "Matchweek 32",
        "Day": "Sat",
        "Venue": "Away",
        "Result": "W",
        "GF": 1,
        "GA": 0,
        "Opponent": "Birmingham City",
        "Poss": 39,
        "Attendance": 19111,
        "Captain": "Steve Morison",
        "Formation": "4-4-2",
        "Referee": "Darren England",
        "Match Report": "Match Report",
        "Notes": null
    },
    {
        "Date": "2018-02-20",
        "Time": "19:45",
        "Comp": "Championship",
        "Round": "Matchweek 33",
        "Day": "Tue",
        "Venue": "Home",
        "Result": "W",
        "GF": 2,
        "GA": 1,
        "Opponent": "Sheffield Weds",
        "Poss": 37,
        "Attendance": 11007,
        "Captain": "Steve Morison",
        "Formation": "4-4-2",
        "Referee": "Peter Bankes",
        "Match Report": "Match Report",
        "Notes": null
    },
    {
        "Date": "2018-02-24",
        "Time": "15:00",
        "Comp": "Championship",
        "Round": "Matchweek 34",
        "Day": "Sat",
        "Venue": "Away",
        "Result": "W",
        "GF": 1,
        "GA": 0,
        "Opponent": "Burton Albion",
        "Poss": 42,
        "Attendance": 4105,
        "Captain": "Steve Morison",
        "Formation": "4-4-2",
        "Referee": "Robert Jones",
        "Match Report": "Match Report",
        "Notes": null
    },
    {
        "Date": "2018-03-03",
        "Time": "15:00",
        "Comp": "Championship",
        "Round": "Matchweek 35",
        "Day": "Sat",
        "Venue": "Home",
        "Result": "D",
        "GF": 1,
        "GA": 1,
        "Opponent": "Sunderland",
        "Poss": 56,
        "Attendance": 14358,
        "Captain": "Steve Morison",
        "Formation": "4-4-2",
        "Referee": "Andrew Davies",
        "Match Report": "Match Report",
        "Notes": null
    },
    {
        "Date": "2018-03-06",
        "Time": "19:45",
        "Comp": "Championship",
        "Round": "Matchweek 36",
        "Day": "Tue",
        "Venue": "Away",
        "Result": "W",
        "GF": 2,
        "GA": 1,
        "Opponent": "Hull City",
        "Poss": 35,
        "Attendance": 13524,
        "Captain": "Shaun Hutchinson",
        "Formation": "4-4-2",
        "Referee": "David Coote",
        "Match Report": "Match Report",
        "Notes": null
    },
    {
        "Date": "2018-03-10",
        "Time": "15:00",
        "Comp": "Championship",
        "Round": "Matchweek 37",
        "Day": "Sat",
        "Venue": "Home",
        "Result": "W",
        "GF": 1,
        "GA": 0,
        "Opponent": "Brentford",
        "Poss": 33,
        "Attendance": 13251,
        "Captain": "Steve Morison",
        "Formation": "4-4-2",
        "Referee": "Stuart Attwell",
        "Match Report": "Match Report",
        "Notes": null
    },
    {
        "Date": "2018-03-17",
        "Time": "13:00",
        "Comp": "Championship",
        "Round": "Matchweek 38",
        "Day": "Sat",
        "Venue": "Away",
        "Result": "W",
        "GF": 2,
        "GA": 0,
        "Opponent": "Barnsley",
        "Poss": 36,
        "Attendance": 13041,
        "Captain": "Steve Morison",
        "Formation": "4-4-2",
        "Referee": "Peter Bankes",
        "Match Report": "Match Report",
        "Notes": null
    },
    {
        "Date": "2018-03-30",
        "Time": "13:00",
        "Comp": "Championship",
        "Round": "Matchweek 39",
        "Day": "Fri",
        "Venue": "Home",
        "Result": "W",
        "GF": 2,
        "GA": 0,
        "Opponent": "Nott'ham Forest",
        "Poss": 35,
        "Attendance": 16004,
        "Captain": "Steve Morison",
        "Formation": "4-4-2",
        "Referee": "Scott Duncan",
        "Match Report": "Match Report",
        "Notes": null
    },
    {
        "Date": "2018-04-02",
        "Time": "15:00",
        "Comp": "Championship",
        "Round": "Matchweek 40",
        "Day": "Mon",
        "Venue": "Away",
        "Result": "D",
        "GF": 2,
        "GA": 2,
        "Opponent": "Ipswich Town",
        "Poss": 44,
        "Attendance": 16010,
        "Captain": "Steve Morison",
        "Formation": "4-4-2",
        "Referee": "Steve Martin",
        "Match Report": "Match Report",
        "Notes": null
    },
    {
        "Date": "2018-04-07",
        "Time": "15:00",
        "Comp": "Championship",
        "Round": "Matchweek 41",
        "Day": "Sat",
        "Venue": "Home",
        "Result": "W",
        "GF": 2,
        "GA": 0,
        "Opponent": "Bristol City",
        "Poss": 37,
        "Attendance": 16081,
        "Captain": "Steve Morison",
        "Formation": "4-4-2",
        "Referee": "Simon Hooper",
        "Match Report": "Match Report",
        "Notes": null
    },
    {
        "Date": "2018-04-10",
        "Time": "20:00",
        "Comp": "Championship",
        "Round": "Matchweek 42",
        "Day": "Tue",
        "Venue": "Away",
        "Result": "W",
        "GF": 2,
        "GA": 0,
        "Opponent": "Bolton",
        "Poss": 45,
        "Attendance": 13810,
        "Captain": "Shaun Hutchinson",
        "Formation": "4-4-2",
        "Referee": "Robert Jones",
        "Match Report": "Match Report",
        "Notes": null
    },
    {
        "Date": "2018-04-14",
        "Time": "13:00",
        "Comp": "Championship",
        "Round": "Matchweek 43",
        "Day": "Sat",
        "Venue": "Away",
        "Result": "D",
        "GF": 1,
        "GA": 1,
        "Opponent": "Sheffield Utd",
        "Poss": 37,
        "Attendance": 27454,
        "Captain": "Steve Morison",
        "Formation": "4-4-2",
        "Referee": "David Coote",
        "Match Report": "Match Report",
        "Notes": null
    },
    {
        "Date": "2018-04-20",
        "Time": "19:45",
        "Comp": "Championship",
        "Round": "Matchweek 44",
        "Day": "Fri",
        "Venue": "Home",
        "Result": "L",
        "GF": 0,
        "GA": 3,
        "Opponent": "Fulham",
        "Poss": 33,
        "Attendance": 17614,
        "Captain": "Steve Morison",
        "Formation": "4-4-2",
        "Referee": "Andre Marriner",
        "Match Report": "Match Report",
        "Notes": null
    },
    {
        "Date": "2018-04-28",
        "Time": "17:30",
        "Comp": "Championship",
        "Round": "Matchweek 45",
        "Day": "Sat",
        "Venue": "Away",
        "Result": "L",
        "GF": 0,
        "GA": 2,
        "Opponent": "Middlesbrough",
        "Poss": 56,
        "Attendance": 28606,
        "Captain": "Steve Morison",
        "Formation": "4-4-2",
        "Referee": "Paul Tierney",
        "Match Report": "Match Report",
        "Notes": null
    },
    {
        "Date": "2018-05-06",
        "Time": "12:30",
        "Comp": "Championship",
        "Round": "Matchweek 46",
        "Day": "Sun",
        "Venue": "Home",
        "Result": "W",
        "GF": 1,
        "GA": 0,
        "Opponent": "Aston Villa",
        "Poss": 40,
        "Attendance": 17195,
        "Captain": "Steve Morison",
        "Formation": "4-4-2",
        "Referee": "Tim Robinson",
        "Match Report": "Match Report",
        "Notes": null
    }
]