[
    {
        "('Unnamed: 0_level_0', 'Player')": "Maxime Biamou",
        "('Unnamed: 1_level_0', '#')": 9.0,
        "('Unnamed: 2_level_0', 'Nation')": "fr FRA",
        "('Unnamed: 3_level_0', 'Pos')": "FW",
        "('Unnamed: 4_level_0', 'Age')": "29-352",
        "('Unnamed: 5_level_0', 'Min')": 90,
        "('Touches', 'Touches')": 32,
        "('Touches', 'Def Pen')": 1,
        "('Touches', 'Def 3rd')": 2,
        "('Touches', 'Mid 3rd')": 14,
        "('Touches', 'Att 3rd')": 16,
        "('Touches', 'Att Pen')": 2,
        "('Touches', 'Live')": 32,
        "('Take-Ons', 'Att')": 0,
        "('Take-Ons', 'Succ')": 0,
        "('Take-Ons', 'Succ%')": null,
        "('Take-Ons', 'Tkld')": 0,
        "('Take-Ons', 'Tkld%')": null,
        "('Carries', 'Carries')": 16,
        "('Carries', 'TotDist')": 91,
        "('Carries', 'PrgDist')": 23,
        "('Carries', 'PrgC')": 1,
        "('Carries', '1/3')": 1,
        "('Carries', 'CPA')": 0,
        "('Carries', 'Mis')": 4,
        "('Carries', 'Dis')": 2,
        "('Receiving', 'Rec')": 22,
        "('Receiving', 'PrgR')": 6
    },
    {
        "('Unnamed: 0_level_0', 'Player')": "Matthew Godden",
        "('Unnamed: 1_level_0', '#')": 24.0,
        "('Unnamed: 2_level_0', 'Nation')": "eng ENG",
        "('Unnamed: 3_level_0', 'Pos')": "FW",
        "('Unnamed: 4_level_0', 'Age')": "29-093",
        "('Unnamed: 5_level_0', 'Min')": 90,
        "('Touches', 'Touches')": 31,
        "('Touches', 'Def Pen')": 2,
        "('Touches', 'Def 3rd')": 4,
        "('Touches', 'Mid 3rd')": 9,
        "('Touches', 'Att 3rd')": 18,
        "('Touches', 'Att Pen')": 4,
        "('Touches', 'Live')": 31,
        "('Take-Ons', 'Att')": 0,
        "('Take-Ons', 'Succ')": 0,
        "('Take-Ons', 'Succ%')": null,
        "('Take-Ons', 'Tkld')": 0,
        "('Take-Ons', 'Tkld%')": null,
        "('Carries', 'Carries')": 12,
        "('Carries', 'TotDist')": 29,
        "('Carries', 'PrgDist')": 10,
        "('Carries', 'PrgC')": 0,
        "('Carries', '1/3')": 0,
        "('Carries', 'CPA')": 0,
        "('Carries', 'Mis')": 2,
        "('Carries', 'Dis')": 0,
        "('Receiving', 'Rec')": 21,
        "('Receiving', 'PrgR')": 9
    },
    {
        "('Unnamed: 0_level_0', 'Player')": "Jordan Shipley",
        "('Unnamed: 1_level_0', '#')": 26.0,
        "('Unnamed: 2_level_0', 'Nation')": "ie IRL",
        "('Unnamed: 3_level_0', 'Pos')": "AM",
        "('Unnamed: 4_level_0', 'Age')": "23-034",
        "('Unnamed: 5_level_0', 'Min')": 87,
        "('Touches', 'Touches')": 47,
        "('Touches', 'Def Pen')": 2,
        "('Touches', 'Def 3rd')": 10,
        "('Touches', 'Mid 3rd')": 24,
        "('Touches', 'Att 3rd')": 14,
        "('Touches', 'Att Pen')": 1,
        "('Touches', 'Live')": 47,
        "('Take-Ons', 'Att')": 2,
        "('Take-Ons', 'Succ')": 1,
        "('Take-Ons', 'Succ%')": 50.0,
        "('Take-Ons', 'Tkld')": 1,
        "('Take-Ons', 'Tkld%')": 50.0,
        "('Carries', 'Carries')": 21,
        "('Carries', 'TotDist')": 82,
        "('Carries', 'PrgDist')": 27,
        "('Carries', 'PrgC')": 1,
        "('Carries', '1/3')": 0,
        "('Carries', 'CPA')": 0,
        "('Carries', 'Mis')": 1,
        "('Carries', 'Dis')": 1,
        "('Receiving', 'Rec')": 25,
        "('Receiving', 'PrgR')": 4
    },
    {
        "('Unnamed: 0_level_0', 'Player')": "Jamie Allen",
        "('Unnamed: 1_level_0', '#')": 8.0,
        "('Unnamed: 2_level_0', 'Nation')": "eng ENG",
        "('Unnamed: 3_level_0', 'Pos')": "AM",
        "('Unnamed: 4_level_0', 'Age')": "25-275",
        "('Unnamed: 5_level_0', 'Min')": 3,
        "('Touches', 'Touches')": 6,
        "('Touches', 'Def Pen')": 0,
        "('Touches', 'Def 3rd')": 3,
        "('Touches', 'Mid 3rd')": 2,
        "('Touches', 'Att 3rd')": 1,
        "('Touches', 'Att Pen')": 0,
        "('Touches', 'Live')": 6,
        "('Take-Ons', 'Att')": 0,
        "('Take-Ons', 'Succ')": 0,
        "('Take-Ons', 'Succ%')": null,
        "('Take-Ons', 'Tkld')": 0,
        "('Take-Ons', 'Tkld%')": null,
        "('Carries', 'Carries')": 0,
        "('Carries', 'TotDist')": 0,
        "('Carries', 'PrgDist')": 0,
        "('Carries', 'PrgC')": 0,
        "('Carries', '1/3')": 0,
        "('Carries', 'CPA')": 0,
        "('Carries', 'Mis')": 0,
        "('Carries', 'Dis')": 0,
        "('Receiving', 'Rec')": 0,
        "('Receiving', 'PrgR')": 0
    },
    {
        "('Unnamed: 0_level_0', 'Player')": "Ben Sheaf",
        "('Unnamed: 1_level_0', '#')": 14.0,
        "('Unnamed: 2_level_0', 'Nation')": "eng ENG",
        "('Unnamed: 3_level_0', 'Pos')": "CM",
        "('Unnamed: 4_level_0', 'Age')": "22-268",
        "('Unnamed: 5_level_0', 'Min')": 90,
        "('Touches', 'Touches')": 58,
        "('Touches', 'Def Pen')": 4,
        "('Touches', 'Def 3rd')": 23,
        "('Touches', 'Mid 3rd')": 29,
        "('Touches', 'Att 3rd')": 6,
        "('Touches', 'Att Pen')": 0,
        "('Touches', 'Live')": 58,
        "('Take-Ons', 'Att')": 0,
        "('Take-Ons', 'Succ')": 0,
        "('Take-Ons', 'Succ%')": null,
        "('Take-Ons', 'Tkld')": 0,
        "('Take-Ons', 'Tkld%')": null,
        "('Carries', 'Carries')": 21,
        "('Carries', 'TotDist')": 124,
        "('Carries', 'PrgDist')": 41,
        "('Carries', 'PrgC')": 0,
        "('Carries', '1/3')": 0,
        "('Carries', 'CPA')": 0,
        "('Carries', 'Mis')": 4,
        "('Carries', 'Dis')": 1,
        "('Receiving', 'Rec')": 33,
        "('Receiving', 'PrgR')": 2
    },
    {
        "('Unnamed: 0_level_0', 'Player')": "Gustavo Hamer",
        "('Unnamed: 1_level_0', '#')": 38.0,
        "('Unnamed: 2_level_0', 'Nation')": "nl NED",
        "('Unnamed: 3_level_0', 'Pos')": "CM",
        "('Unnamed: 4_level_0', 'Age')": "23-128",
        "('Unnamed: 5_level_0', 'Min')": 72,
        "('Touches', 'Touches')": 58,
        "('Touches', 'Def Pen')": 0,
        "('Touches', 'Def 3rd')": 7,
        "('Touches', 'Mid 3rd')": 35,
        "('Touches', 'Att 3rd')": 16,
        "('Touches', 'Att Pen')": 0,
        "('Touches', 'Live')": 58,
        "('Take-Ons', 'Att')": 0,
        "('Take-Ons', 'Succ')": 0,
        "('Take-Ons', 'Succ%')": null,
        "('Take-Ons', 'Tkld')": 0,
        "('Take-Ons', 'Tkld%')": null,
        "('Carries', 'Carries')": 24,
        "('Carries', 'TotDist')": 90,
        "('Carries', 'PrgDist')": 36,
        "('Carries', 'PrgC')": 0,
        "('Carries', '1/3')": 1,
        "('Carries', 'CPA')": 0,
        "('Carries', 'Mis')": 2,
        "('Carries', 'Dis')": 6,
        "('Receiving', 'Rec')": 40,
        "('Receiving', 'PrgR')": 2
    },
    {
        "('Unnamed: 0_level_0', 'Player')": "Callum O'Hare",
        "('Unnamed: 1_level_0', '#')": 11.0,
        "('Unnamed: 2_level_0', 'Nation')": "eng ENG",
        "('Unnamed: 3_level_0', 'Pos')": "CM",
        "('Unnamed: 4_level_0', 'Age')": "22-182",
        "('Unnamed: 5_level_0', 'Min')": 18,
        "('Touches', 'Touches')": 9,
        "('Touches', 'Def Pen')": 0,
        "('Touches', 'Def 3rd')": 2,
        "('Touches', 'Mid 3rd')": 5,
        "('Touches', 'Att 3rd')": 2,
        "('Touches', 'Att Pen')": 1,
        "('Touches', 'Live')": 9,
        "('Take-Ons', 'Att')": 0,
        "('Take-Ons', 'Succ')": 0,
        "('Take-Ons', 'Succ%')": null,
        "('Take-Ons', 'Tkld')": 0,
        "('Take-Ons', 'Tkld%')": null,
        "('Carries', 'Carries')": 6,
        "('Carries', 'TotDist')": 26,
        "('Carries', 'PrgDist')": 3,
        "('Carries', 'PrgC')": 0,
        "('Carries', '1/3')": 1,
        "('Carries', 'CPA')": 0,
        "('Carries', 'Mis')": 0,
        "('Carries', 'Dis')": 0,
        "('Receiving', 'Rec')": 7,
        "('Receiving', 'PrgR')": 1
    },
    {
        "('Unnamed: 0_level_0', 'Player')": "Ryan John Giles",
        "('Unnamed: 1_level_0', '#')": 18.0,
        "('Unnamed: 2_level_0', 'Nation')": "eng ENG",
        "('Unnamed: 3_level_0', 'Pos')": "WB",
        "('Unnamed: 4_level_0', 'Age')": "20-278",
        "('Unnamed: 5_level_0', 'Min')": 90,
        "('Touches', 'Touches')": 50,
        "('Touches', 'Def Pen')": 1,
        "('Touches', 'Def 3rd')": 18,
        "('Touches', 'Mid 3rd')": 18,
        "('Touches', 'Att 3rd')": 14,
        "('Touches', 'Att Pen')": 1,
        "('Touches', 'Live')": 50,
        "('Take-Ons', 'Att')": 1,
        "('Take-Ons', 'Succ')": 1,
        "('Take-Ons', 'Succ%')": 100.0,
        "('Take-Ons', 'Tkld')": 0,
        "('Take-Ons', 'Tkld%')": 0.0,
        "('Carries', 'Carries')": 27,
        "('Carries', 'TotDist')": 202,
        "('Carries', 'PrgDist')": 104,
        "('Carries', 'PrgC')": 4,
        "('Carries', '1/3')": 2,
        "('Carries', 'CPA')": 0,
        "('Carries', 'Mis')": 0,
        "('Carries', 'Dis')": 1,
        "('Receiving', 'Rec')": 31,
        "('Receiving', 'PrgR')": 5
    },
    {
        "('Unnamed: 0_level_0', 'Player')": "Fankaty Dabo",
        "('Unnamed: 1_level_0', '#')": 23.0,
        "('Unnamed: 2_level_0', 'Nation')": "eng ENG",
        "('Unnamed: 3_level_0', 'Pos')": "WB",
        "('Unnamed: 4_level_0', 'Age')": "25-019",
        "('Unnamed: 5_level_0', 'Min')": 81,
        "('Touches', 'Touches')": 60,
        "('Touches', 'Def Pen')": 3,
        "('Touches', 'Def 3rd')": 22,
        "('Touches', 'Mid 3rd')": 19,
        "('Touches', 'Att 3rd')": 19,
        "('Touches', 'Att Pen')": 2,
        "('Touches', 'Live')": 60,
        "('Take-Ons', 'Att')": 3,
        "('Take-Ons', 'Succ')": 1,
        "('Take-Ons', 'Succ%')": 33.3,
        "('Take-Ons', 'Tkld')": 2,
        "('Take-Ons', 'Tkld%')": 66.7,
        "('Carries', 'Carries')": 25,
        "('Carries', 'TotDist')": 165,
        "('Carries', 'PrgDist')": 82,
        "('Carries', 'PrgC')": 4,
        "('Carries', '1/3')": 2,
        "('Carries', 'CPA')": 0,
        "('Carries', 'Mis')": 0,
        "('Carries', 'Dis')": 2,
        "('Receiving', 'Rec')": 32,
        "('Receiving', 'PrgR')": 3
    },
    {
        "('Unnamed: 0_level_0', 'Player')": "Sam McCallum",
        "('Unnamed: 1_level_0', '#')": 21.0,
        "('Unnamed: 2_level_0', 'Nation')": "eng ENG",
        "('Unnamed: 3_level_0', 'Pos')": "WB",
        "('Unnamed: 4_level_0', 'Age')": "20-058",
        "('Unnamed: 5_level_0', 'Min')": 9,
        "('Touches', 'Touches')": 7,
        "('Touches', 'Def Pen')": 3,
        "('Touches', 'Def 3rd')": 5,
        "('Touches', 'Mid 3rd')": 1,
        "('Touches', 'Att 3rd')": 1,
        "('Touches', 'Att Pen')": 0,
        "('Touches', 'Live')": 7,
        "('Take-Ons', 'Att')": 0,
        "('Take-Ons', 'Succ')": 0,
        "('Take-Ons', 'Succ%')": null,
        "('Take-Ons', 'Tkld')": 0,
        "('Take-Ons', 'Tkld%')": null,
        "('Carries', 'Carries')": 1,
        "('Carries', 'TotDist')": 14,
        "('Carries', 'PrgDist')": 5,
        "('Carries', 'PrgC')": 0,
        "('Carries', '1/3')": 0,
        "('Carries', 'CPA')": 0,
        "('Carries', 'Mis')": 0,
        "('Carries', 'Dis')": 0,
        "('Receiving', 'Rec')": 3,
        "('Receiving', 'PrgR')": 1
    },
    {
        "('Unnamed: 0_level_0', 'Player')": "Dominic Hyam",
        "('Unnamed: 1_level_0', '#')": 15.0,
        "('Unnamed: 2_level_0', 'Nation')": "sct SCO",
        "('Unnamed: 3_level_0', 'Pos')": "CB",
        "('Unnamed: 4_level_0', 'Age')": "24-315",
        "('Unnamed: 5_level_0', 'Min')": 90,
        "('Touches', 'Touches')": 47,
        "('Touches', 'Def Pen')": 6,
        "('Touches', 'Def 3rd')": 29,
        "('Touches', 'Mid 3rd')": 18,
        "('Touches', 'Att 3rd')": 0,
        "('Touches', 'Att Pen')": 0,
        "('Touches', 'Live')": 47,
        "('Take-Ons', 'Att')": 0,
        "('Take-Ons', 'Succ')": 0,
        "('Take-Ons', 'Succ%')": null,
        "('Take-Ons', 'Tkld')": 0,
        "('Take-Ons', 'Tkld%')": null,
        "('Carries', 'Carries')": 20,
        "('Carries', 'TotDist')": 110,
        "('Carries', 'PrgDist')": 68,
        "('Carries', 'PrgC')": 0,
        "('Carries', '1/3')": 0,
        "('Carries', 'CPA')": 0,
        "('Carries', 'Mis')": 0,
        "('Carries', 'Dis')": 0,
        "('Receiving', 'Rec')": 30,
        "('Receiving', 'PrgR')": 0
    },
    {
        "('Unnamed: 0_level_0', 'Player')": "Leo Skiri \u00d8stig\u00e5rd",
        "('Unnamed: 1_level_0', '#')": 2.0,
        "('Unnamed: 2_level_0', 'Nation')": "no NOR",
        "('Unnamed: 3_level_0', 'Pos')": "CB",
        "('Unnamed: 4_level_0', 'Age')": "20-337",
        "('Unnamed: 5_level_0', 'Min')": 90,
        "('Touches', 'Touches')": 41,
        "('Touches', 'Def Pen')": 8,
        "('Touches', 'Def 3rd')": 25,
        "('Touches', 'Mid 3rd')": 14,
        "('Touches', 'Att 3rd')": 2,
        "('Touches', 'Att Pen')": 2,
        "('Touches', 'Live')": 41,
        "('Take-Ons', 'Att')": 1,
        "('Take-Ons', 'Succ')": 0,
        "('Take-Ons', 'Succ%')": 0.0,
        "('Take-Ons', 'Tkld')": 1,
        "('Take-Ons', 'Tkld%')": 100.0,
        "('Carries', 'Carries')": 18,
        "('Carries', 'TotDist')": 81,
        "('Carries', 'PrgDist')": 36,
        "('Carries', 'PrgC')": 0,
        "('Carries', '1/3')": 0,
        "('Carries', 'CPA')": 0,
        "('Carries', 'Mis')": 1,
        "('Carries', 'Dis')": 0,
        "('Receiving', 'Rec')": 19,
        "('Receiving', 'PrgR')": 0
    },
    {
        "('Unnamed: 0_level_0', 'Player')": "Michael Rose",
        "('Unnamed: 1_level_0', '#')": 4.0,
        "('Unnamed: 2_level_0', 'Nation')": "sct SCO",
        "('Unnamed: 3_level_0', 'Pos')": "CB",
        "('Unnamed: 4_level_0', 'Age')": "25-019",
        "('Unnamed: 5_level_0', 'Min')": 90,
        "('Touches', 'Touches')": 49,
        "('Touches', 'Def Pen')": 7,
        "('Touches', 'Def 3rd')": 35,
        "('Touches', 'Mid 3rd')": 13,
        "('Touches', 'Att 3rd')": 1,
        "('Touches', 'Att Pen')": 0,
        "('Touches', 'Live')": 49,
        "('Take-Ons', 'Att')": 0,
        "('Take-Ons', 'Succ')": 0,
        "('Take-Ons', 'Succ%')": null,
        "('Take-Ons', 'Tkld')": 0,
        "('Take-Ons', 'Tkld%')": null,
        "('Carries', 'Carries')": 20,
        "('Carries', 'TotDist')": 90,
        "('Carries', 'PrgDist')": 53,
        "('Carries', 'PrgC')": 0,
        "('Carries', '1/3')": 0,
        "('Carries', 'CPA')": 0,
        "('Carries', 'Mis')": 0,
        "('Carries', 'Dis')": 0,
        "('Receiving', 'Rec')": 34,
        "('Receiving', 'PrgR')": 0
    },
    {
        "('Unnamed: 0_level_0', 'Player')": "Marko Maro\u0161i",
        "('Unnamed: 1_level_0', '#')": 1.0,
        "('Unnamed: 2_level_0', 'Nation')": "sk SVK",
        "('Unnamed: 3_level_0', 'Pos')": "GK",
        "('Unnamed: 4_level_0', 'Age')": "27-007",
        "('Unnamed: 5_level_0', 'Min')": 90,
        "('Touches', 'Touches')": 35,
        "('Touches', 'Def Pen')": 32,
        "('Touches', 'Def 3rd')": 35,
        "('Touches', 'Mid 3rd')": 0,
        "('Touches', 'Att 3rd')": 0,
        "('Touches', 'Att Pen')": 0,
        "('Touches', 'Live')": 35,
        "('Take-Ons', 'Att')": 0,
        "('Take-Ons', 'Succ')": 0,
        "('Take-Ons', 'Succ%')": null,
        "('Take-Ons', 'Tkld')": 0,
        "('Take-Ons', 'Tkld%')": null,
        "('Carries', 'Carries')": 15,
        "('Carries', 'TotDist')": 87,
        "('Carries', 'PrgDist')": 43,
        "('Carries', 'PrgC')": 0,
        "('Carries', '1/3')": 0,
        "('Carries', 'CPA')": 0,
        "('Carries', 'Mis')": 0,
        "('Carries', 'Dis')": 0,
        "('Receiving', 'Rec')": 11,
        "('Receiving', 'PrgR')": 0
    },
    {
        "('Unnamed: 0_level_0', 'Player')": "14 Players",
        "('Unnamed: 1_level_0', '#')": null,
        "('Unnamed: 2_level_0', 'Nation')": null,
        "('Unnamed: 3_level_0', 'Pos')": null,
        "('Unnamed: 4_level_0', 'Age')": null,
        "('Unnamed: 5_level_0', 'Min')": 990,
        "('Touches', 'Touches')": 530,
        "('Touches', 'Def Pen')": 69,
        "('Touches', 'Def 3rd')": 220,
        "('Touches', 'Mid 3rd')": 201,
        "('Touches', 'Att 3rd')": 110,
        "('Touches', 'Att Pen')": 13,
        "('Touches', 'Live')": 530,
        "('Take-Ons', 'Att')": 7,
        "('Take-Ons', 'Succ')": 3,
        "('Take-Ons', 'Succ%')": 42.9,
        "('Take-Ons', 'Tkld')": 4,
        "('Take-Ons', 'Tkld%')": 57.1,
        "('Carries', 'Carries')": 226,
        "('Carries', 'TotDist')": 1191,
        "('Carries', 'PrgDist')": 531,
        "('Carries', 'PrgC')": 10,
        "('Carries', '1/3')": 7,
        "('Carries', 'CPA')": 0,
        "('Carries', 'Mis')": 14,
        "('Carries', 'Dis')": 13,
        "('Receiving', 'Rec')": 308,
        "('Receiving', 'PrgR')": 33
    }
]